simple_rest_server/__init__.py
simple_rest_server/rest_server.py
simple_rest_server-1.0.5.dist-info/LICENSE
simple_rest_server-1.0.5.dist-info/METADATA
simple_rest_server-1.0.5.dist-info/WHEEL
simple_rest_server-1.0.5.dist-info/top_level.txt
simple_rest_server-1.0.5.dist-info/RECORD
