Metadata-Version: 2.1
Name: simple-rest-server
Version: 1.0.5
Summary: simple rest server based on flask, useful for rest rest integration testing
Home-page: https://gitlab.com/pavel_lavi/simple-rest-server
Author: Pavel Lavi
Author-email: LaviPavel@outlook.com
License: MIT
Platform: any
Classifier: Intended Audience :: Developers
Classifier: Topic :: Software Development :: Libraries
Classifier: Programming Language :: Python :: 3.7
Classifier: Programming Language :: Python :: 3.8
Classifier: Programming Language :: Python :: 3.9
Classifier: Programming Language :: Python :: 3.10
Classifier: License :: OSI Approved :: MIT License
Classifier: Operating System :: OS Independent
Requires-Python: >=3.6
License-File: LICENSE
